{
  "collection": "app_settings",
  "field": "foods_ratings_average_display",
  "type": "boolean",
  "meta": {
    "collection": "app_settings",
    "conditions": null,
    "display": null,
    "display_options": null,
    "field": "foods_ratings_average_display",
    "group": "foods_settings",
    "hidden": false,
    "interface": "boolean",
    "note": "Soll die durschnittliche Bewertung der Speisen angezeigt werden?",
    "options": null,
    "readonly": false,
    "required": false,
    "sort": 11,
    "special": [
      "cast-boolean"
    ],
    "translations": [
      {
        "language": "de-DE",
        "translation": "Speise Bewertungen Durchschnitt Anzeigen"
      }
    ],
    "validation": null,
    "validation_message": null,
    "width": "half"
  },
  "schema": {
    "name": "foods_ratings_average_display",
    "table": "app_settings",
    "data_type": "boolean",
    "default_value": true,
    "max_length": null,
    "numeric_precision": null,
    "numeric_scale": null,
    "is_nullable": true,
    "is_unique": false,
    "is_indexed": false,
    "is_primary_key": false,
    "is_generated": false,
    "generation_expression": null,
    "has_auto_increment": false,
    "foreign_key_table": null,
    "foreign_key_column": null
  }
}
